{
  "project_info": {
    "project_number": "579714998961",
    "firebase_url": "https://maga-1a240.firebaseio.com",
    "project_id": "maga-1a240",
    "storage_bucket": "maga-1a240.appspot.com"
  },
  "client": [
    {
      "client_info": {
        "mobilesdk_app_id": "1:579714998961:android:7bd5b24ab70bbdbeb4b890",
        "android_client_info": {
          "package_name": "com.flutterAppAndroid.maga_app"
        }
      },
      "oauth_client": [
        {
          "client_id": "579714998961-s05mui8o9j9d26sfmdajg5bcgmor18mi.apps.googleusercontent.com",
          "client_type": 3
        }
      ],
      "api_key": [
        {
          "current_key": "AIzaSyD1pswl894vMSK_RqT8-CQJsAKIA2Q9epo"
        }
      ],
      "services": {
        "appinvite_service": {
          "other_platform_oauth_client": [
            {
              "client_id": "579714998961-s05mui8o9j9d26sfmdajg5bcgmor18mi.apps.googleusercontent.com",
              "client_type": 3
            }
          ]
        }
      }
    }
  ],
  "configuration_version": "1"
}